<?xml version="1.0" encoding="ISO-8859-1"?>
<fmiModelDescription fmiVersion="3.0-alpha.3" modelName="Resource" instantiationToken="{7b9c2114-2ce5-4076-a138-2cbc69e069e5}">

  <ModelExchange modelIdentifier="Resource"/>

  <BasicCoSimulation modelIdentifier="Resource" canHandleVariableCommunicationStepSize="true"/>

  <LogCategories>
    <Category name="logEvents" description="Log events"/>
    <Category name="logStatusError" description="Log error messages"/>
  </LogCategories>

  <DefaultExperiment startTime="0" stopTime="1"/>

  <ModelVariables>
    <Int32 name="y" valueReference="0" description="Value of the first character in resources/y.txt" causality="output"/>
  </ModelVariables>

  <ModelStructure>
    <Output valueReference="0"/>
  </ModelStructure>

</fmiModelDescription>
